<?xml version="1.0" encoding="UTF-8"?>

<!-- generated on 2025-04-29 05:34:27 by Eclipse SUMO sumo Version 1.20.0
<configuration xmlns:xsi="http://www.w3.org/2001/XMLSchema-instance" xsi:noNamespaceSchemaLocation="http://sumo.dlr.de/xsd/sumoConfiguration.xsd">

    <input>
        <net-file value="nets/2lane_unprotected_right/2lane_unprotected_right.net.xml"/>
        <route-files value="nets/2lane_unprotected_right/2lane_unprotected_right.rou.xml"/>
    </input>

    <output>
        <tripinfo-output value="traces/transs50f1_s50_f0.5_random/0070_tripinfo.xml"/>
        <collision-output value="traces/transs50f1_s50_f0.5_random/0070_collisions.xml"/>
        <statistic-output value="traces/transs50f1_s50_f0.5_random/0070_statistics.xml"/>
    </output>

    <processing>
        <collision.action value="teleport"/>
        <collision.check-junctions value="true"/>
        <time-to-teleport value="-1"/>
        <waiting-time-memory value="1000"/>
        <max-depart-delay value="-1"/>
        <default.speeddev value="0.1"/>
    </processing>

    <report>
        <no-warnings value="true"/>
    </report>

    <ssm_device>
        <device.ssm.probability value="1.0"/>
        <device.ssm.measures value="BR"/>
        <device.ssm.file value="/Users/finn/Code/CausalKnowledgeTransfer-4-SafeRL/traces/transs50f1_s50_f0.5_random/0070_ssm.xml"/>
    </ssm_device>

    <traci_server>
        <remote-port value="63278"/>
    </traci_server>

    <random_number>
        <random value="true"/>
    </random_number>

</configuration>
-->

<collisions xmlns:xsi="http://www.w3.org/2001/XMLSchema-instance" xsi:noNamespaceSchemaLocation="http://sumo.dlr.de/xsd/collision_file.xsd">
    <collision time="1501.00" type="collision" lane="junctionEast_0" pos="11.48" collider="westEastBottom1200.33" victim="southEast.145" colliderType="carCustom" victimType="carCustom" colliderSpeed="14.53" victimSpeed="8.18"/>
    <collision time="1516.00" type="collision" lane="junctionEast_0" pos="0.32" collider="southEast.149" victim="westEastBottom1200.34" colliderType="carCustom" victimType="carCustom" colliderSpeed="5.48" victimSpeed="6.95"/>
    <collision time="2447.00" type="collision" lane="junctionEast_0" pos="0.58" collider="southEast.235" victim="westEastBottom2400.3" colliderType="carCustom" victimType="carCustom" colliderSpeed="4.67" victimSpeed="16.25"/>
    <collision time="2668.00" type="collision" lane="junctionEast_0" pos="4.90" collider="westEastBottom2400.24" victim="southEast.263" colliderType="carCustom" victimType="carCustom" colliderSpeed="9.71" victimSpeed="6.71"/>
    <collision time="2948.00" type="collision" lane="junctionEast_0" pos="2.69" collider="westEastBottom2400.47" victim="southEast.284" colliderType="carCustom" victimType="carCustom" colliderSpeed="11.01" victimSpeed="7.26"/>
</collisions>
