<?xml version="1.0" encoding="UTF-8"?>

<!-- generated on 2025-04-29 07:33:00 by Eclipse SUMO sumo Version 1.20.0
<configuration xmlns:xsi="http://www.w3.org/2001/XMLSchema-instance" xsi:noNamespaceSchemaLocation="http://sumo.dlr.de/xsd/sumoConfiguration.xsd">

    <input>
        <net-file value="nets/2lane_unprotected_right/2lane_unprotected_right.net.xml"/>
        <route-files value="nets/2lane_unprotected_right/2lane_unprotected_right.rou.xml"/>
    </input>

    <output>
        <tripinfo-output value="traces/transs50f0.5_s50_f1_random/0114_tripinfo.xml"/>
        <collision-output value="traces/transs50f0.5_s50_f1_random/0114_collisions.xml"/>
        <statistic-output value="traces/transs50f0.5_s50_f1_random/0114_statistics.xml"/>
    </output>

    <processing>
        <collision.action value="teleport"/>
        <collision.check-junctions value="true"/>
        <time-to-teleport value="-1"/>
        <waiting-time-memory value="1000"/>
        <max-depart-delay value="-1"/>
        <default.speeddev value="0.1"/>
    </processing>

    <report>
        <no-warnings value="true"/>
    </report>

    <ssm_device>
        <device.ssm.probability value="1.0"/>
        <device.ssm.measures value="BR"/>
        <device.ssm.file value="/Users/finn/Code/CausalKnowledgeTransfer-4-SafeRL/traces/transs50f0.5_s50_f1_random/0114_ssm.xml"/>
    </ssm_device>

    <traci_server>
        <remote-port value="63815"/>
    </traci_server>

    <random_number>
        <random value="true"/>
    </random_number>

</configuration>
-->

<statistics xmlns:xsi="http://www.w3.org/2001/XMLSchema-instance" xsi:noNamespaceSchemaLocation="http://sumo.dlr.de/xsd/statistic_file.xsd">
    <performance clockBegin="1745904780.91" clockEnd="1745904825.51" clockDuration="44.60" traciDuration="43.37" realTimeFactor="80.72" vehicleUpdatesPerSecond="5139.63" personUpdatesPerSecond="0.00" begin="0.00" end="3600.00" duration="3600.00"/>
    <vehicles loaded="1562" inserted="1470" running="69" waiting="92"/>
    <teleports total="20" jam="0" yield="0" wrongLane="0"/>
    <safety collisions="20" emergencyStops="13" emergencyBraking="778"/>
    <persons loaded="0" running="0" jammed="0"/>
    <personTeleports total="0" abortWait="0" wrongDest="0"/>
    <vehicleTripStatistics count="1401" routeLength="993.62" speed="8.30" duration="157.42" waitingTime="5.24" timeLoss="112.30" departDelay="27.46" departDelayWaiting="-1.00" totalTravelTime="220540.00" totalDepartDelay="38473.41"/>
    <pedestrianStatistics number="0" routeLength="0.00" duration="0.00" timeLoss="0.00"/>
    <rideStatistics number="0"/>
    <transportStatistics number="0"/>
</statistics>
